{
  "coord": { "lon": -79.4163, "lat": 43.7001 },
  "weather": [
    {
      "id": 801,
      "main": "Clouds",
      "description": "few clouds",
      "icon": "02d"
    }
  ],
  "base": "stations",
  "main": {
    "temp": 294.34,
    "feels_like": 294.47,
    "temp_min": 293.76,
    "temp_max": 296.2,
    "pressure": 1013,
    "humidity": 75,
    "sea_level": 1013,
    "grnd_level": 998
  },
  "visibility": 10000,
  "wind": { "speed": 4.92, "deg": 140, "gust": 0 },
  "clouds": { "all": 20 },
  "dt": 1751286263,
  "sys": {
    "type": 2,
    "id": 2099289,
    "country": "CA",
    "sunrise": 1751276357,
    "sunset": 1751331792
  },
  "timezone": -14400,
  "id": 6167865,
  "name": "Toronto",
  "cod": 200
}
